.gitlab-ci.yml
.travis.yml
CHANGES.rst
CONTRIBUTORS.rst
DEVELOP.rst
LICENSE.GPL
LICENSE.rst
MANIFEST.in
README.rst
constraints.txt
constraints_plone52.txt
requirements.txt
setup.cfg
setup.py
tox.ini
docs/conf.py
docs/index.rst
src/collective/__init__.py
src/collective.renderfiletypes.egg-info/PKG-INFO
src/collective.renderfiletypes.egg-info/SOURCES.txt
src/collective.renderfiletypes.egg-info/dependency_links.txt
src/collective.renderfiletypes.egg-info/entry_points.txt
src/collective.renderfiletypes.egg-info/namespace_packages.txt
src/collective.renderfiletypes.egg-info/not-zip-safe
src/collective.renderfiletypes.egg-info/requires.txt
src/collective.renderfiletypes.egg-info/top_level.txt
src/collective/renderfiletypes/__init__.py
src/collective/renderfiletypes/configure.zcml
src/collective/renderfiletypes/interfaces.py
src/collective/renderfiletypes/permissions.zcml
src/collective/renderfiletypes/setuphandlers.py
src/collective/renderfiletypes/testing.py
src/collective/renderfiletypes/utils.py
src/collective/renderfiletypes/browser/__init__.py
src/collective/renderfiletypes/browser/configure.zcml
src/collective/renderfiletypes/filters/__init__.py
src/collective/renderfiletypes/filters/configure.zcml
src/collective/renderfiletypes/filters/render_file_types.py
src/collective/renderfiletypes/locales/README.rst
src/collective/renderfiletypes/locales/__init__.py
src/collective/renderfiletypes/locales/collective.renderfiletypes.pot
src/collective/renderfiletypes/locales/update.py
src/collective/renderfiletypes/locales/update.sh
src/collective/renderfiletypes/locales/en/LC_MESSAGES/collective.renderfiletypes.mo
src/collective/renderfiletypes/locales/en/LC_MESSAGES/collective.renderfiletypes.po
src/collective/renderfiletypes/profiles/default/browserlayer.xml
src/collective/renderfiletypes/profiles/default/catalog.xml
src/collective/renderfiletypes/profiles/default/metadata.xml
src/collective/renderfiletypes/profiles/default/registry.xml
src/collective/renderfiletypes/profiles/default/rolemap.xml
src/collective/renderfiletypes/profiles/uninstall/browserlayer.xml
src/collective/renderfiletypes/profiles/uninstall/registry.xml
src/collective/renderfiletypes/tests/__init__.py
src/collective/renderfiletypes/tests/test_robot.py
src/collective/renderfiletypes/tests/test_setup.py
src/collective/renderfiletypes/tests/test_upgrade_step_1001.py
src/collective/renderfiletypes/tests/robot/test_example.robot
