Metadata-Version: 2.1
Name: collective.renderfiletypes
Version: 2.0b6
Summary: An addon to render file type information next to the links
Home-page: https://github.com/collective/collective.renderfiletypes
Author: Mikel Larreategi
Author-email: mlarreategi@codesyntax.com
License: GPL version 2
Project-URL: PyPI, https://pypi.python.org/pypi/collective.renderfiletypes
Project-URL: Source, https://github.com/collective/collective.renderfiletypes
Project-URL: Tracker, https://github.com/collective/collective.renderfiletypes/issues
Keywords: Python Plone
Platform: UNKNOWN
Classifier: Environment :: Web Environment
Classifier: Framework :: Plone
Classifier: Framework :: Plone :: Addon
Classifier: Framework :: Plone :: 5.2
Classifier: Programming Language :: Python
Classifier: Programming Language :: Python :: 2.7
Classifier: Programming Language :: Python :: 3.6
Classifier: Programming Language :: Python :: 3.7
Classifier: Operating System :: OS Independent
Classifier: License :: OSI Approved :: GNU General Public License v2 (GPLv2)
Requires-Python: ==2.7, >=3.6
Provides-Extra: test
